README.txt
setup.py
zmqfan/__init__.py
zmqfan/zmqsub.py
zmqfan.egg-info/PKG-INFO
zmqfan.egg-info/SOURCES.txt
zmqfan.egg-info/dependency_links.txt
zmqfan.egg-info/requires.txt
zmqfan.egg-info/top_level.txt