Metadata-Version: 1.0
Name: zmqfan
Version: 0.7.0
Summary: ZMQFan zeromq helper wrappers.
Home-page: https://github.com/eastein/zmqfan/
Author: Eric Stein
Author-email: toba@des.truct.org
License: UNKNOWN
Platform: UNKNOWN
